[
{
    "model": "dashboard.room",
    "pk": 1,
    "fields": {
        "number": 1
    }
},
{
    "model": "dashboard.room",
    "pk": 2,
    "fields": {
        "number": 2
    }
},
{
    "model": "dashboard.room",
    "pk": 3,
    "fields": {
        "number": 3
    }
},
{
    "model": "dashboard.room",
    "pk": 4,
    "fields": {
        "number": 4
    }
},
{
    "model": "dashboard.room",
    "pk": 5,
    "fields": {
        "number": 5
    }
},
{
    "model": "dashboard.room",
    "pk": 6,
    "fields": {
        "number": 6
    }
},
{
    "model": "dashboard.room",
    "pk": 7,
    "fields": {
        "number": 7
    }
},
{
    "model": "dashboard.room",
    "pk": 8,
    "fields": {
        "number": 8
    }
},
{
    "model": "dashboard.room",
    "pk": 9,
    "fields": {
        "number": 9
    }
},
{
    "model": "dashboard.room",
    "pk": 10,
    "fields": {
        "number": 10
    }
},
{
    "model": "dashboard.room",
    "pk": 11,
    "fields": {
        "number": 11
    }
},
{
    "model": "dashboard.room",
    "pk": 12,
    "fields": {
        "number": 12
    }
},
{
    "model": "dashboard.room",
    "pk": 13,
    "fields": {
        "number": 13
    }
},
{
    "model": "dashboard.room",
    "pk": 14,
    "fields": {
        "number": 14
    }
},
{
    "model": "dashboard.room",
    "pk": 15,
    "fields": {
        "number": 15
    }
},
{
    "model": "dashboard.room",
    "pk": 16,
    "fields": {
        "number": 16
    }
},
{
    "model": "dashboard.room",
    "pk": 17,
    "fields": {
        "number": 17
    }
},
{
    "model": "dashboard.room",
    "pk": 18,
    "fields": {
        "number": 18
    }
},
{
    "model": "dashboard.room",
    "pk": 19,
    "fields": {
        "number": 19
    }
},
{
    "model": "dashboard.room",
    "pk": 20,
    "fields": {
        "number": 20
    }
},
{
    "model": "dashboard.room",
    "pk": 21,
    "fields": {
        "number": 21
    }
},
{
    "model": "dashboard.room",
    "pk": 22,
    "fields": {
        "number": 22
    }
},
{
    "model": "dashboard.room",
    "pk": 23,
    "fields": {
        "number": 23
    }
},
{
    "model": "dashboard.room",
    "pk": 24,
    "fields": {
        "number": 24
    }
},
{
    "model": "dashboard.room",
    "pk": 25,
    "fields": {
        "number": 25
    }
},
{
    "model": "dashboard.room",
    "pk": 26,
    "fields": {
        "number": 26
    }
},
{
    "model": "dashboard.room",
    "pk": 27,
    "fields": {
        "number": 27
    }
},
{
    "model": "dashboard.room",
    "pk": 28,
    "fields": {
        "number": 28
    }
},
{
    "model": "dashboard.room",
    "pk": 29,
    "fields": {
        "number": 29
    }
},
{
    "model": "dashboard.room",
    "pk": 30,
    "fields": {
        "number": 30
    }
},
{
    "model": "dashboard.room",
    "pk": 31,
    "fields": {
        "number": 31
    }
},
{
    "model": "dashboard.room",
    "pk": 32,
    "fields": {
        "number": 32
    }
},
{
    "model": "dashboard.room",
    "pk": 33,
    "fields": {
        "number": 33
    }
},
{
    "model": "dashboard.room",
    "pk": 34,
    "fields": {
        "number": 34
    }
},
{
    "model": "dashboard.room",
    "pk": 35,
    "fields": {
        "number": 35
    }
},
{
    "model": "dashboard.room",
    "pk": 36,
    "fields": {
        "number": 36
    }
},
{
    "model": "dashboard.room",
    "pk": 37,
    "fields": {
        "number": 37
    }
},
{
    "model": "dashboard.room",
    "pk": 38,
    "fields": {
        "number": 38
    }
},
{
    "model": "dashboard.room",
    "pk": 39,
    "fields": {
        "number": 39
    }
},
{
    "model": "dashboard.room",
    "pk": 40,
    "fields": {
        "number": 40
    }
},
{
    "model": "dashboard.room",
    "pk": 41,
    "fields": {
        "number": 41
    }
},
{
    "model": "dashboard.room",
    "pk": 42,
    "fields": {
        "number": 42
    }
},
{
    "model": "dashboard.room",
    "pk": 43,
    "fields": {
        "number": 43
    }
},
{
    "model": "dashboard.room",
    "pk": 44,
    "fields": {
        "number": 44
    }
},
{
    "model": "dashboard.room",
    "pk": 45,
    "fields": {
        "number": 45
    }
},
{
    "model": "dashboard.room",
    "pk": 46,
    "fields": {
        "number": 46
    }
},
{
    "model": "dashboard.room",
    "pk": 47,
    "fields": {
        "number": 47
    }
},
{
    "model": "dashboard.room",
    "pk": 48,
    "fields": {
        "number": 48
    }
},
{
    "model": "dashboard.room",
    "pk": 49,
    "fields": {
        "number": 49
    }
},
{
    "model": "dashboard.room",
    "pk": 50,
    "fields": {
        "number": 50
    }
},
{
    "model": "dashboard.room",
    "pk": 51,
    "fields": {
        "number": 51
    }
},
{
    "model": "dashboard.room",
    "pk": 52,
    "fields": {
        "number": 52
    }
},
{
    "model": "dashboard.room",
    "pk": 53,
    "fields": {
        "number": 53
    }
},
{
    "model": "dashboard.room",
    "pk": 54,
    "fields": {
        "number": 54
    }
},
{
    "model": "dashboard.room",
    "pk": 55,
    "fields": {
        "number": 55
    }
},
{
    "model": "dashboard.room",
    "pk": 56,
    "fields": {
        "number": 56
    }
},
{
    "model": "dashboard.room",
    "pk": 57,
    "fields": {
        "number": 57
    }
},
{
    "model": "dashboard.room",
    "pk": 58,
    "fields": {
        "number": 58
    }
},
{
    "model": "dashboard.room",
    "pk": 59,
    "fields": {
        "number": 59
    }
},
{
    "model": "dashboard.room",
    "pk": 60,
    "fields": {
        "number": 60
    }
},
{
    "model": "dashboard.room",
    "pk": 61,
    "fields": {
        "number": 61
    }
},
{
    "model": "dashboard.room",
    "pk": 62,
    "fields": {
        "number": 62
    }
},
{
    "model": "dashboard.room",
    "pk": 63,
    "fields": {
        "number": 63
    }
},
{
    "model": "dashboard.room",
    "pk": 64,
    "fields": {
        "number": 64
    }
},
{
    "model": "dashboard.room",
    "pk": 65,
    "fields": {
        "number": 65
    }
},
{
    "model": "dashboard.room",
    "pk": 66,
    "fields": {
        "number": 66
    }
},
{
    "model": "dashboard.room",
    "pk": 67,
    "fields": {
        "number": 67
    }
},
{
    "model": "dashboard.room",
    "pk": 68,
    "fields": {
        "number": 68
    }
},
{
    "model": "dashboard.room",
    "pk": 69,
    "fields": {
        "number": 69
    }
},
{
    "model": "dashboard.room",
    "pk": 70,
    "fields": {
        "number": 70
    }
},
{
    "model": "dashboard.room",
    "pk": 71,
    "fields": {
        "number": 71
    }
},
{
    "model": "dashboard.room",
    "pk": 72,
    "fields": {
        "number": 72
    }
},
{
    "model": "dashboard.room",
    "pk": 73,
    "fields": {
        "number": 73
    }
},
{
    "model": "dashboard.room",
    "pk": 74,
    "fields": {
        "number": 74
    }
},
{
    "model": "dashboard.room",
    "pk": 75,
    "fields": {
        "number": 75
    }
},
{
    "model": "dashboard.room",
    "pk": 76,
    "fields": {
        "number": 76
    }
},
{
    "model": "dashboard.room",
    "pk": 77,
    "fields": {
        "number": 77
    }
},
{
    "model": "dashboard.room",
    "pk": 78,
    "fields": {
        "number": 78
    }
},
{
    "model": "dashboard.room",
    "pk": 79,
    "fields": {
        "number": 79
    }
},
{
    "model": "dashboard.room",
    "pk": 80,
    "fields": {
        "number": 80
    }
},
{
    "model": "dashboard.room",
    "pk": 81,
    "fields": {
        "number": 81
    }
},
{
    "model": "dashboard.room",
    "pk": 82,
    "fields": {
        "number": 82
    }
},
{
    "model": "dashboard.room",
    "pk": 83,
    "fields": {
        "number": 83
    }
},
{
    "model": "dashboard.room",
    "pk": 84,
    "fields": {
        "number": 84
    }
},
{
    "model": "dashboard.room",
    "pk": 85,
    "fields": {
        "number": 85
    }
},
{
    "model": "dashboard.room",
    "pk": 86,
    "fields": {
        "number": 86
    }
},
{
    "model": "dashboard.room",
    "pk": 87,
    "fields": {
        "number": 87
    }
},
{
    "model": "dashboard.room",
    "pk": 88,
    "fields": {
        "number": 88
    }
},
{
    "model": "dashboard.room",
    "pk": 89,
    "fields": {
        "number": 89
    }
},
{
    "model": "dashboard.room",
    "pk": 90,
    "fields": {
        "number": 90
    }
},
{
    "model": "dashboard.room",
    "pk": 91,
    "fields": {
        "number": 91
    }
},
{
    "model": "dashboard.room",
    "pk": 92,
    "fields": {
        "number": 92
    }
},
{
    "model": "dashboard.room",
    "pk": 93,
    "fields": {
        "number": 93
    }
},
{
    "model": "dashboard.room",
    "pk": 94,
    "fields": {
        "number": 94
    }
},
{
    "model": "dashboard.room",
    "pk": 95,
    "fields": {
        "number": 95
    }
},
{
    "model": "dashboard.room",
    "pk": 96,
    "fields": {
        "number": 96
    }
},
{
    "model": "dashboard.room",
    "pk": 97,
    "fields": {
        "number": 97
    }
},
{
    "model": "dashboard.room",
    "pk": 98,
    "fields": {
        "number": 98
    }
},
{
    "model": "dashboard.room",
    "pk": 99,
    "fields": {
        "number": 99
    }
},
{
    "model": "dashboard.room",
    "pk": 100,
    "fields": {
        "number": 100
    }
},
{
    "model": "dashboard.room",
    "pk": 101,
    "fields": {
        "number": 101
    }
},
{
    "model": "dashboard.room",
    "pk": 102,
    "fields": {
        "number": 102
    }
},
{
    "model": "dashboard.room",
    "pk": 103,
    "fields": {
        "number": 103
    }
},
{
    "model": "dashboard.room",
    "pk": 104,
    "fields": {
        "number": 104
    }
},
{
    "model": "dashboard.room",
    "pk": 105,
    "fields": {
        "number": 105
    }
},
{
    "model": "dashboard.room",
    "pk": 106,
    "fields": {
        "number": 106
    }
},
{
    "model": "dashboard.room",
    "pk": 107,
    "fields": {
        "number": 107
    }
},
{
    "model": "dashboard.room",
    "pk": 108,
    "fields": {
        "number": 108
    }
},
{
    "model": "dashboard.room",
    "pk": 109,
    "fields": {
        "number": 109
    }
},
{
    "model": "dashboard.room",
    "pk": 110,
    "fields": {
        "number": 110
    }
},
{
    "model": "dashboard.room",
    "pk": 111,
    "fields": {
        "number": 111
    }
},
{
    "model": "dashboard.room",
    "pk": 112,
    "fields": {
        "number": 112
    }
},
{
    "model": "dashboard.room",
    "pk": 113,
    "fields": {
        "number": 113
    }
},
{
    "model": "dashboard.room",
    "pk": 114,
    "fields": {
        "number": 114
    }
},
{
    "model": "dashboard.room",
    "pk": 115,
    "fields": {
        "number": 115
    }
},
{
    "model": "dashboard.room",
    "pk": 116,
    "fields": {
        "number": 116
    }
},
{
    "model": "dashboard.room",
    "pk": 117,
    "fields": {
        "number": 117
    }
},
{
    "model": "dashboard.room",
    "pk": 118,
    "fields": {
        "number": 118
    }
},
{
    "model": "dashboard.room",
    "pk": 119,
    "fields": {
        "number": 119
    }
},
{
    "model": "dashboard.room",
    "pk": 120,
    "fields": {
        "number": 120
    }
},
{
    "model": "dashboard.room",
    "pk": 121,
    "fields": {
        "number": 121
    }
},
{
    "model": "dashboard.room",
    "pk": 122,
    "fields": {
        "number": 122
    }
},
{
    "model": "dashboard.room",
    "pk": 123,
    "fields": {
        "number": 123
    }
},
{
    "model": "dashboard.room",
    "pk": 124,
    "fields": {
        "number": 124
    }
},
{
    "model": "dashboard.room",
    "pk": 125,
    "fields": {
        "number": 125
    }
},
{
    "model": "dashboard.room",
    "pk": 126,
    "fields": {
        "number": 126
    }
},
{
    "model": "dashboard.room",
    "pk": 127,
    "fields": {
        "number": 127
    }
},
{
    "model": "dashboard.room",
    "pk": 128,
    "fields": {
        "number": 128
    }
},
{
    "model": "dashboard.room",
    "pk": 129,
    "fields": {
        "number": 129
    }
},
{
    "model": "dashboard.room",
    "pk": 130,
    "fields": {
        "number": 130
    }
},
{
    "model": "dashboard.room",
    "pk": 131,
    "fields": {
        "number": 131
    }
},
{
    "model": "dashboard.room",
    "pk": 132,
    "fields": {
        "number": 132
    }
},
{
    "model": "dashboard.room",
    "pk": 133,
    "fields": {
        "number": 133
    }
},
{
    "model": "dashboard.room",
    "pk": 134,
    "fields": {
        "number": 134
    }
},
{
    "model": "dashboard.room",
    "pk": 135,
    "fields": {
        "number": 135
    }
},
{
    "model": "dashboard.room",
    "pk": 136,
    "fields": {
        "number": 136
    }
},
{
    "model": "dashboard.room",
    "pk": 137,
    "fields": {
        "number": 137
    }
},
{
    "model": "dashboard.room",
    "pk": 138,
    "fields": {
        "number": 138
    }
},
{
    "model": "dashboard.room",
    "pk": 139,
    "fields": {
        "number": 139
    }
},
{
    "model": "dashboard.room",
    "pk": 140,
    "fields": {
        "number": 140
    }
},
{
    "model": "dashboard.room",
    "pk": 141,
    "fields": {
        "number": 141
    }
},
{
    "model": "dashboard.room",
    "pk": 142,
    "fields": {
        "number": 142
    }
},
{
    "model": "dashboard.room",
    "pk": 143,
    "fields": {
        "number": 143
    }
},
{
    "model": "dashboard.room",
    "pk": 144,
    "fields": {
        "number": 144
    }
},
{
    "model": "dashboard.room",
    "pk": 145,
    "fields": {
        "number": 145
    }
},
{
    "model": "dashboard.room",
    "pk": 146,
    "fields": {
        "number": 146
    }
},
{
    "model": "dashboard.room",
    "pk": 147,
    "fields": {
        "number": 147
    }
},
{
    "model": "dashboard.room",
    "pk": 148,
    "fields": {
        "number": 148
    }
},
{
    "model": "dashboard.room",
    "pk": 149,
    "fields": {
        "number": 149
    }
},
{
    "model": "dashboard.room",
    "pk": 150,
    "fields": {
        "number": 150
    }
},
{
    "model": "dashboard.room",
    "pk": 151,
    "fields": {
        "number": 151
    }
},
{
    "model": "dashboard.room",
    "pk": 152,
    "fields": {
        "number": 152
    }
},
{
    "model": "dashboard.room",
    "pk": 153,
    "fields": {
        "number": 153
    }
},
{
    "model": "dashboard.room",
    "pk": 154,
    "fields": {
        "number": 154
    }
},
{
    "model": "dashboard.room",
    "pk": 155,
    "fields": {
        "number": 155
    }
},
{
    "model": "dashboard.room",
    "pk": 156,
    "fields": {
        "number": 156
    }
},
{
    "model": "dashboard.room",
    "pk": 157,
    "fields": {
        "number": 157
    }
},
{
    "model": "dashboard.room",
    "pk": 158,
    "fields": {
        "number": 158
    }
},
{
    "model": "dashboard.room",
    "pk": 159,
    "fields": {
        "number": 159
    }
},
{
    "model": "dashboard.room",
    "pk": 160,
    "fields": {
        "number": 160
    }
},
{
    "model": "dashboard.room",
    "pk": 161,
    "fields": {
        "number": 161
    }
},
{
    "model": "dashboard.room",
    "pk": 162,
    "fields": {
        "number": 162
    }
},
{
    "model": "dashboard.room",
    "pk": 163,
    "fields": {
        "number": 163
    }
},
{
    "model": "dashboard.room",
    "pk": 164,
    "fields": {
        "number": 164
    }
},
{
    "model": "dashboard.room",
    "pk": 165,
    "fields": {
        "number": 165
    }
},
{
    "model": "dashboard.room",
    "pk": 166,
    "fields": {
        "number": 166
    }
},
{
    "model": "dashboard.room",
    "pk": 167,
    "fields": {
        "number": 167
    }
},
{
    "model": "dashboard.room",
    "pk": 168,
    "fields": {
        "number": 168
    }
},
{
    "model": "dashboard.room",
    "pk": 169,
    "fields": {
        "number": 169
    }
},
{
    "model": "dashboard.room",
    "pk": 170,
    "fields": {
        "number": 170
    }
},
{
    "model": "dashboard.room",
    "pk": 171,
    "fields": {
        "number": 171
    }
},
{
    "model": "dashboard.room",
    "pk": 172,
    "fields": {
        "number": 172
    }
},
{
    "model": "dashboard.room",
    "pk": 173,
    "fields": {
        "number": 173
    }
},
{
    "model": "dashboard.room",
    "pk": 174,
    "fields": {
        "number": 174
    }
},
{
    "model": "dashboard.room",
    "pk": 175,
    "fields": {
        "number": 175
    }
},
{
    "model": "dashboard.room",
    "pk": 176,
    "fields": {
        "number": 176
    }
},
{
    "model": "dashboard.room",
    "pk": 177,
    "fields": {
        "number": 177
    }
},
{
    "model": "dashboard.room",
    "pk": 178,
    "fields": {
        "number": 178
    }
},
{
    "model": "dashboard.room",
    "pk": 179,
    "fields": {
        "number": 179
    }
},
{
    "model": "dashboard.room",
    "pk": 180,
    "fields": {
        "number": 180
    }
},
{
    "model": "dashboard.room",
    "pk": 181,
    "fields": {
        "number": 181
    }
},
{
    "model": "dashboard.room",
    "pk": 182,
    "fields": {
        "number": 182
    }
},
{
    "model": "dashboard.room",
    "pk": 183,
    "fields": {
        "number": 183
    }
},
{
    "model": "dashboard.room",
    "pk": 184,
    "fields": {
        "number": 184
    }
},
{
    "model": "dashboard.room",
    "pk": 185,
    "fields": {
        "number": 185
    }
},
{
    "model": "dashboard.room",
    "pk": 186,
    "fields": {
        "number": 186
    }
},
{
    "model": "dashboard.room",
    "pk": 187,
    "fields": {
        "number": 187
    }
},
{
    "model": "dashboard.room",
    "pk": 188,
    "fields": {
        "number": 188
    }
},
{
    "model": "dashboard.room",
    "pk": 189,
    "fields": {
        "number": 189
    }
},
{
    "model": "dashboard.room",
    "pk": 190,
    "fields": {
        "number": 190
    }
},
{
    "model": "dashboard.room",
    "pk": 191,
    "fields": {
        "number": 191
    }
},
{
    "model": "dashboard.room",
    "pk": 192,
    "fields": {
        "number": 192
    }
},
{
    "model": "dashboard.room",
    "pk": 193,
    "fields": {
        "number": 193
    }
},
{
    "model": "dashboard.room",
    "pk": 194,
    "fields": {
        "number": 194
    }
},
{
    "model": "dashboard.room",
    "pk": 195,
    "fields": {
        "number": 195
    }
},
{
    "model": "dashboard.room",
    "pk": 196,
    "fields": {
        "number": 196
    }
},
{
    "model": "dashboard.room",
    "pk": 197,
    "fields": {
        "number": 197
    }
},
{
    "model": "dashboard.room",
    "pk": 198,
    "fields": {
        "number": 198
    }
},
{
    "model": "dashboard.room",
    "pk": 199,
    "fields": {
        "number": 199
    }
},
{
    "model": "dashboard.room",
    "pk": 200,
    "fields": {
        "number": 200
    }
},
{
    "model": "dashboard.room",
    "pk": 201,
    "fields": {
        "number": 201
    }
},
{
    "model": "dashboard.room",
    "pk": 202,
    "fields": {
        "number": 202
    }
},
{
    "model": "dashboard.room",
    "pk": 203,
    "fields": {
        "number": 203
    }
},
{
    "model": "dashboard.room",
    "pk": 204,
    "fields": {
        "number": 204
    }
},
{
    "model": "dashboard.room",
    "pk": 205,
    "fields": {
        "number": 205
    }
},
{
    "model": "dashboard.room",
    "pk": 206,
    "fields": {
        "number": 206
    }
},
{
    "model": "dashboard.room",
    "pk": 207,
    "fields": {
        "number": 207
    }
},
{
    "model": "dashboard.room",
    "pk": 208,
    "fields": {
        "number": 208
    }
},
{
    "model": "dashboard.room",
    "pk": 209,
    "fields": {
        "number": 209
    }
},
{
    "model": "dashboard.room",
    "pk": 210,
    "fields": {
        "number": 210
    }
},
{
    "model": "dashboard.room",
    "pk": 211,
    "fields": {
        "number": 211
    }
},
{
    "model": "dashboard.room",
    "pk": 212,
    "fields": {
        "number": 212
    }
},
{
    "model": "dashboard.room",
    "pk": 213,
    "fields": {
        "number": 213
    }
},
{
    "model": "dashboard.room",
    "pk": 214,
    "fields": {
        "number": 214
    }
},
{
    "model": "dashboard.room",
    "pk": 215,
    "fields": {
        "number": 215
    }
},
{
    "model": "dashboard.room",
    "pk": 216,
    "fields": {
        "number": 216
    }
},
{
    "model": "dashboard.room",
    "pk": 217,
    "fields": {
        "number": 217
    }
},
{
    "model": "dashboard.room",
    "pk": 218,
    "fields": {
        "number": 218
    }
},
{
    "model": "dashboard.room",
    "pk": 219,
    "fields": {
        "number": 219
    }
},
{
    "model": "dashboard.room",
    "pk": 220,
    "fields": {
        "number": 220
    }
},
{
    "model": "dashboard.room",
    "pk": 221,
    "fields": {
        "number": 221
    }
},
{
    "model": "dashboard.room",
    "pk": 222,
    "fields": {
        "number": 222
    }
},
{
    "model": "dashboard.room",
    "pk": 223,
    "fields": {
        "number": 223
    }
},
{
    "model": "dashboard.room",
    "pk": 224,
    "fields": {
        "number": 224
    }
},
{
    "model": "dashboard.room",
    "pk": 225,
    "fields": {
        "number": 225
    }
},
{
    "model": "dashboard.room",
    "pk": 226,
    "fields": {
        "number": 226
    }
},
{
    "model": "dashboard.room",
    "pk": 227,
    "fields": {
        "number": 227
    }
},
{
    "model": "dashboard.room",
    "pk": 228,
    "fields": {
        "number": 228
    }
},
{
    "model": "dashboard.room",
    "pk": 229,
    "fields": {
        "number": 229
    }
},
{
    "model": "dashboard.room",
    "pk": 230,
    "fields": {
        "number": 230
    }
},
{
    "model": "dashboard.room",
    "pk": 231,
    "fields": {
        "number": 231
    }
},
{
    "model": "dashboard.room",
    "pk": 232,
    "fields": {
        "number": 232
    }
},
{
    "model": "dashboard.room",
    "pk": 233,
    "fields": {
        "number": 233
    }
},
{
    "model": "dashboard.room",
    "pk": 234,
    "fields": {
        "number": 234
    }
},
{
    "model": "dashboard.room",
    "pk": 235,
    "fields": {
        "number": 235
    }
},
{
    "model": "dashboard.room",
    "pk": 236,
    "fields": {
        "number": 236
    }
},
{
    "model": "dashboard.room",
    "pk": 237,
    "fields": {
        "number": 237
    }
},
{
    "model": "dashboard.room",
    "pk": 238,
    "fields": {
        "number": 238
    }
},
{
    "model": "dashboard.room",
    "pk": 239,
    "fields": {
        "number": 239
    }
},
{
    "model": "dashboard.room",
    "pk": 240,
    "fields": {
        "number": 240
    }
},
{
    "model": "dashboard.room",
    "pk": 241,
    "fields": {
        "number": 241
    }
},
{
    "model": "dashboard.room",
    "pk": 242,
    "fields": {
        "number": 242
    }
},
{
    "model": "dashboard.room",
    "pk": 243,
    "fields": {
        "number": 243
    }
},
{
    "model": "dashboard.room",
    "pk": 244,
    "fields": {
        "number": 244
    }
},
{
    "model": "dashboard.room",
    "pk": 245,
    "fields": {
        "number": 245
    }
},
{
    "model": "dashboard.room",
    "pk": 246,
    "fields": {
        "number": 246
    }
},
{
    "model": "dashboard.room",
    "pk": 247,
    "fields": {
        "number": 247
    }
},
{
    "model": "dashboard.room",
    "pk": 248,
    "fields": {
        "number": 248
    }
},
{
    "model": "dashboard.room",
    "pk": 249,
    "fields": {
        "number": 249
    }
},
{
    "model": "dashboard.room",
    "pk": 250,
    "fields": {
        "number": 250
    }
},
{
    "model": "dashboard.room",
    "pk": 251,
    "fields": {
        "number": 251
    }
},
{
    "model": "dashboard.room",
    "pk": 252,
    "fields": {
        "number": 252
    }
},
{
    "model": "dashboard.room",
    "pk": 253,
    "fields": {
        "number": 253
    }
},
{
    "model": "dashboard.room",
    "pk": 254,
    "fields": {
        "number": 254
    }
},
{
    "model": "dashboard.room",
    "pk": 255,
    "fields": {
        "number": 255
    }
},
{
    "model": "dashboard.room",
    "pk": 256,
    "fields": {
        "number": 256
    }
},
{
    "model": "dashboard.room",
    "pk": 257,
    "fields": {
        "number": 257
    }
},
{
    "model": "dashboard.room",
    "pk": 258,
    "fields": {
        "number": 258
    }
},
{
    "model": "dashboard.room",
    "pk": 259,
    "fields": {
        "number": 259
    }
},
{
    "model": "dashboard.room",
    "pk": 260,
    "fields": {
        "number": 260
    }
},
{
    "model": "dashboard.room",
    "pk": 261,
    "fields": {
        "number": 261
    }
},
{
    "model": "dashboard.room",
    "pk": 262,
    "fields": {
        "number": 262
    }
},
{
    "model": "dashboard.room",
    "pk": 263,
    "fields": {
        "number": 263
    }
},
{
    "model": "dashboard.room",
    "pk": 264,
    "fields": {
        "number": 264
    }
},
{
    "model": "dashboard.room",
    "pk": 265,
    "fields": {
        "number": 265
    }
},
{
    "model": "dashboard.room",
    "pk": 266,
    "fields": {
        "number": 266
    }
},
{
    "model": "dashboard.room",
    "pk": 267,
    "fields": {
        "number": 267
    }
},
{
    "model": "dashboard.room",
    "pk": 268,
    "fields": {
        "number": 268
    }
},
{
    "model": "dashboard.room",
    "pk": 269,
    "fields": {
        "number": 269
    }
},
{
    "model": "dashboard.room",
    "pk": 270,
    "fields": {
        "number": 270
    }
},
{
    "model": "dashboard.room",
    "pk": 271,
    "fields": {
        "number": 271
    }
},
{
    "model": "dashboard.room",
    "pk": 272,
    "fields": {
        "number": 272
    }
},
{
    "model": "dashboard.room",
    "pk": 273,
    "fields": {
        "number": 273
    }
},
{
    "model": "dashboard.room",
    "pk": 274,
    "fields": {
        "number": 274
    }
},
{
    "model": "dashboard.room",
    "pk": 275,
    "fields": {
        "number": 275
    }
},
{
    "model": "dashboard.room",
    "pk": 276,
    "fields": {
        "number": 276
    }
},
{
    "model": "dashboard.room",
    "pk": 277,
    "fields": {
        "number": 277
    }
},
{
    "model": "dashboard.room",
    "pk": 278,
    "fields": {
        "number": 278
    }
},
{
    "model": "dashboard.room",
    "pk": 279,
    "fields": {
        "number": 279
    }
},
{
    "model": "dashboard.room",
    "pk": 280,
    "fields": {
        "number": 280
    }
},
{
    "model": "dashboard.room",
    "pk": 281,
    "fields": {
        "number": 281
    }
},
{
    "model": "dashboard.room",
    "pk": 282,
    "fields": {
        "number": 282
    }
},
{
    "model": "dashboard.room",
    "pk": 283,
    "fields": {
        "number": 283
    }
},
{
    "model": "dashboard.room",
    "pk": 284,
    "fields": {
        "number": 284
    }
},
{
    "model": "dashboard.room",
    "pk": 285,
    "fields": {
        "number": 285
    }
},
{
    "model": "dashboard.room",
    "pk": 286,
    "fields": {
        "number": 286
    }
},
{
    "model": "dashboard.room",
    "pk": 287,
    "fields": {
        "number": 287
    }
},
{
    "model": "dashboard.room",
    "pk": 288,
    "fields": {
        "number": 288
    }
},
{
    "model": "dashboard.room",
    "pk": 289,
    "fields": {
        "number": 289
    }
},
{
    "model": "dashboard.room",
    "pk": 290,
    "fields": {
        "number": 290
    }
},
{
    "model": "dashboard.room",
    "pk": 291,
    "fields": {
        "number": 291
    }
},
{
    "model": "dashboard.room",
    "pk": 292,
    "fields": {
        "number": 292
    }
},
{
    "model": "dashboard.room",
    "pk": 293,
    "fields": {
        "number": 293
    }
},
{
    "model": "dashboard.room",
    "pk": 294,
    "fields": {
        "number": 294
    }
},
{
    "model": "dashboard.room",
    "pk": 295,
    "fields": {
        "number": 295
    }
},
{
    "model": "dashboard.room",
    "pk": 296,
    "fields": {
        "number": 296
    }
},
{
    "model": "dashboard.room",
    "pk": 297,
    "fields": {
        "number": 297
    }
},
{
    "model": "dashboard.room",
    "pk": 298,
    "fields": {
        "number": 298
    }
},
{
    "model": "dashboard.room",
    "pk": 299,
    "fields": {
        "number": 299
    }
},
{
    "model": "dashboard.room",
    "pk": 300,
    "fields": {
        "number": 300
    }
},
{
    "model": "dashboard.room",
    "pk": 301,
    "fields": {
        "number": 301
    }
},
{
    "model": "dashboard.room",
    "pk": 302,
    "fields": {
        "number": 302
    }
},
{
    "model": "dashboard.room",
    "pk": 303,
    "fields": {
        "number": 303
    }
},
{
    "model": "dashboard.room",
    "pk": 304,
    "fields": {
        "number": 304
    }
},
{
    "model": "dashboard.room",
    "pk": 305,
    "fields": {
        "number": 305
    }
},
{
    "model": "dashboard.room",
    "pk": 306,
    "fields": {
        "number": 306
    }
},
{
    "model": "dashboard.room",
    "pk": 307,
    "fields": {
        "number": 307
    }
},
{
    "model": "dashboard.room",
    "pk": 308,
    "fields": {
        "number": 308
    }
},
{
    "model": "dashboard.room",
    "pk": 309,
    "fields": {
        "number": 309
    }
},
{
    "model": "dashboard.room",
    "pk": 310,
    "fields": {
        "number": 310
    }
},
{
    "model": "dashboard.room",
    "pk": 311,
    "fields": {
        "number": 311
    }
},
{
    "model": "dashboard.room",
    "pk": 312,
    "fields": {
        "number": 312
    }
},
{
    "model": "dashboard.room",
    "pk": 313,
    "fields": {
        "number": 313
    }
},
{
    "model": "dashboard.room",
    "pk": 314,
    "fields": {
        "number": 314
    }
},
{
    "model": "dashboard.room",
    "pk": 315,
    "fields": {
        "number": 315
    }
},
{
    "model": "dashboard.room",
    "pk": 316,
    "fields": {
        "number": 316
    }
},
{
    "model": "dashboard.room",
    "pk": 317,
    "fields": {
        "number": 317
    }
},
{
    "model": "dashboard.room",
    "pk": 318,
    "fields": {
        "number": 318
    }
},
{
    "model": "dashboard.room",
    "pk": 319,
    "fields": {
        "number": 319
    }
},
{
    "model": "dashboard.room",
    "pk": 320,
    "fields": {
        "number": 320
    }
},
{
    "model": "dashboard.room",
    "pk": 321,
    "fields": {
        "number": 321
    }
},
{
    "model": "dashboard.room",
    "pk": 322,
    "fields": {
        "number": 322
    }
},
{
    "model": "dashboard.room",
    "pk": 323,
    "fields": {
        "number": 323
    }
},
{
    "model": "dashboard.room",
    "pk": 324,
    "fields": {
        "number": 324
    }
},
{
    "model": "dashboard.room",
    "pk": 325,
    "fields": {
        "number": 325
    }
},
{
    "model": "dashboard.room",
    "pk": 326,
    "fields": {
        "number": 326
    }
},
{
    "model": "dashboard.room",
    "pk": 327,
    "fields": {
        "number": 327
    }
},
{
    "model": "dashboard.room",
    "pk": 328,
    "fields": {
        "number": 328
    }
},
{
    "model": "dashboard.room",
    "pk": 329,
    "fields": {
        "number": 329
    }
},
{
    "model": "dashboard.room",
    "pk": 330,
    "fields": {
        "number": 330
    }
},
{
    "model": "dashboard.room",
    "pk": 331,
    "fields": {
        "number": 331
    }
},
{
    "model": "dashboard.room",
    "pk": 332,
    "fields": {
        "number": 332
    }
},
{
    "model": "dashboard.room",
    "pk": 333,
    "fields": {
        "number": 333
    }
},
{
    "model": "dashboard.room",
    "pk": 334,
    "fields": {
        "number": 334
    }
},
{
    "model": "dashboard.room",
    "pk": 335,
    "fields": {
        "number": 335
    }
},
{
    "model": "dashboard.room",
    "pk": 336,
    "fields": {
        "number": 336
    }
},
{
    "model": "dashboard.room",
    "pk": 337,
    "fields": {
        "number": 337
    }
},
{
    "model": "dashboard.room",
    "pk": 338,
    "fields": {
        "number": 338
    }
},
{
    "model": "dashboard.room",
    "pk": 339,
    "fields": {
        "number": 339
    }
},
{
    "model": "dashboard.room",
    "pk": 340,
    "fields": {
        "number": 340
    }
},
{
    "model": "dashboard.room",
    "pk": 341,
    "fields": {
        "number": 341
    }
},
{
    "model": "dashboard.room",
    "pk": 342,
    "fields": {
        "number": 342
    }
},
{
    "model": "dashboard.room",
    "pk": 343,
    "fields": {
        "number": 343
    }
},
{
    "model": "dashboard.room",
    "pk": 344,
    "fields": {
        "number": 344
    }
},
{
    "model": "dashboard.room",
    "pk": 345,
    "fields": {
        "number": 345
    }
},
{
    "model": "dashboard.room",
    "pk": 346,
    "fields": {
        "number": 346
    }
},
{
    "model": "dashboard.room",
    "pk": 347,
    "fields": {
        "number": 347
    }
},
{
    "model": "dashboard.room",
    "pk": 348,
    "fields": {
        "number": 348
    }
},
{
    "model": "dashboard.room",
    "pk": 349,
    "fields": {
        "number": 349
    }
},
{
    "model": "dashboard.room",
    "pk": 350,
    "fields": {
        "number": 350
    }
},
{
    "model": "dashboard.room",
    "pk": 351,
    "fields": {
        "number": 351
    }
},
{
    "model": "dashboard.room",
    "pk": 352,
    "fields": {
        "number": 352
    }
},
{
    "model": "dashboard.room",
    "pk": 353,
    "fields": {
        "number": 353
    }
},
{
    "model": "dashboard.room",
    "pk": 354,
    "fields": {
        "number": 354
    }
},
{
    "model": "dashboard.room",
    "pk": 355,
    "fields": {
        "number": 355
    }
},
{
    "model": "dashboard.room",
    "pk": 356,
    "fields": {
        "number": 356
    }
},
{
    "model": "dashboard.room",
    "pk": 357,
    "fields": {
        "number": 357
    }
},
{
    "model": "dashboard.room",
    "pk": 358,
    "fields": {
        "number": 358
    }
},
{
    "model": "dashboard.room",
    "pk": 359,
    "fields": {
        "number": 359
    }
},
{
    "model": "dashboard.room",
    "pk": 360,
    "fields": {
        "number": 360
    }
},
{
    "model": "dashboard.room",
    "pk": 361,
    "fields": {
        "number": 361
    }
},
{
    "model": "dashboard.room",
    "pk": 362,
    "fields": {
        "number": 362
    }
},
{
    "model": "dashboard.room",
    "pk": 363,
    "fields": {
        "number": 363
    }
},
{
    "model": "dashboard.room",
    "pk": 364,
    "fields": {
        "number": 364
    }
},
{
    "model": "dashboard.room",
    "pk": 365,
    "fields": {
        "number": 365
    }
},
{
    "model": "dashboard.room",
    "pk": 366,
    "fields": {
        "number": 366
    }
},
{
    "model": "dashboard.room",
    "pk": 367,
    "fields": {
        "number": 367
    }
},
{
    "model": "dashboard.room",
    "pk": 368,
    "fields": {
        "number": 368
    }
},
{
    "model": "dashboard.room",
    "pk": 369,
    "fields": {
        "number": 369
    }
},
{
    "model": "dashboard.room",
    "pk": 370,
    "fields": {
        "number": 370
    }
},
{
    "model": "dashboard.room",
    "pk": 371,
    "fields": {
        "number": 371
    }
},
{
    "model": "dashboard.room",
    "pk": 372,
    "fields": {
        "number": 372
    }
},
{
    "model": "dashboard.room",
    "pk": 373,
    "fields": {
        "number": 373
    }
},
{
    "model": "dashboard.room",
    "pk": 374,
    "fields": {
        "number": 374
    }
},
{
    "model": "dashboard.room",
    "pk": 375,
    "fields": {
        "number": 375
    }
},
{
    "model": "dashboard.room",
    "pk": 376,
    "fields": {
        "number": 376
    }
},
{
    "model": "dashboard.room",
    "pk": 377,
    "fields": {
        "number": 377
    }
},
{
    "model": "dashboard.room",
    "pk": 378,
    "fields": {
        "number": 378
    }
},
{
    "model": "dashboard.room",
    "pk": 379,
    "fields": {
        "number": 379
    }
},
{
    "model": "dashboard.room",
    "pk": 380,
    "fields": {
        "number": 380
    }
},
{
    "model": "dashboard.room",
    "pk": 381,
    "fields": {
        "number": 381
    }
},
{
    "model": "dashboard.room",
    "pk": 382,
    "fields": {
        "number": 382
    }
},
{
    "model": "dashboard.room",
    "pk": 383,
    "fields": {
        "number": 383
    }
},
{
    "model": "dashboard.room",
    "pk": 384,
    "fields": {
        "number": 384
    }
},
{
    "model": "dashboard.room",
    "pk": 385,
    "fields": {
        "number": 385
    }
},
{
    "model": "dashboard.room",
    "pk": 386,
    "fields": {
        "number": 386
    }
},
{
    "model": "dashboard.room",
    "pk": 387,
    "fields": {
        "number": 387
    }
},
{
    "model": "dashboard.room",
    "pk": 388,
    "fields": {
        "number": 388
    }
},
{
    "model": "dashboard.room",
    "pk": 389,
    "fields": {
        "number": 389
    }
},
{
    "model": "dashboard.room",
    "pk": 390,
    "fields": {
        "number": 390
    }
},
{
    "model": "dashboard.room",
    "pk": 391,
    "fields": {
        "number": 391
    }
},
{
    "model": "dashboard.room",
    "pk": 392,
    "fields": {
        "number": 392
    }
},
{
    "model": "dashboard.room",
    "pk": 393,
    "fields": {
        "number": 393
    }
},
{
    "model": "dashboard.room",
    "pk": 394,
    "fields": {
        "number": 394
    }
},
{
    "model": "dashboard.room",
    "pk": 395,
    "fields": {
        "number": 395
    }
},
{
    "model": "dashboard.room",
    "pk": 396,
    "fields": {
        "number": 396
    }
},
{
    "model": "dashboard.room",
    "pk": 397,
    "fields": {
        "number": 397
    }
},
{
    "model": "dashboard.room",
    "pk": 398,
    "fields": {
        "number": 398
    }
},
{
    "model": "dashboard.room",
    "pk": 399,
    "fields": {
        "number": 399
    }
},
{
    "model": "dashboard.room",
    "pk": 400,
    "fields": {
        "number": 400
    }
},
{
    "model": "dashboard.room",
    "pk": 401,
    "fields": {
        "number": 401
    }
},
{
    "model": "dashboard.room",
    "pk": 402,
    "fields": {
        "number": 402
    }
},
{
    "model": "dashboard.room",
    "pk": 403,
    "fields": {
        "number": 403
    }
},
{
    "model": "dashboard.room",
    "pk": 404,
    "fields": {
        "number": 404
    }
},
{
    "model": "dashboard.room",
    "pk": 405,
    "fields": {
        "number": 405
    }
},
{
    "model": "dashboard.room",
    "pk": 406,
    "fields": {
        "number": 406
    }
},
{
    "model": "dashboard.room",
    "pk": 407,
    "fields": {
        "number": 407
    }
},
{
    "model": "dashboard.room",
    "pk": 408,
    "fields": {
        "number": 408
    }
},
{
    "model": "dashboard.room",
    "pk": 409,
    "fields": {
        "number": 409
    }
},
{
    "model": "dashboard.room",
    "pk": 410,
    "fields": {
        "number": 410
    }
},
{
    "model": "dashboard.room",
    "pk": 411,
    "fields": {
        "number": 411
    }
},
{
    "model": "dashboard.room",
    "pk": 412,
    "fields": {
        "number": 412
    }
},
{
    "model": "dashboard.room",
    "pk": 413,
    "fields": {
        "number": 413
    }
},
{
    "model": "dashboard.room",
    "pk": 414,
    "fields": {
        "number": 414
    }
},
{
    "model": "dashboard.room",
    "pk": 415,
    "fields": {
        "number": 415
    }
},
{
    "model": "dashboard.room",
    "pk": 416,
    "fields": {
        "number": 416
    }
},
{
    "model": "dashboard.room",
    "pk": 417,
    "fields": {
        "number": 417
    }
},
{
    "model": "dashboard.room",
    "pk": 418,
    "fields": {
        "number": 418
    }
},
{
    "model": "dashboard.room",
    "pk": 419,
    "fields": {
        "number": 419
    }
},
{
    "model": "dashboard.room",
    "pk": 420,
    "fields": {
        "number": 420
    }
},
{
    "model": "dashboard.room",
    "pk": 421,
    "fields": {
        "number": 421
    }
},
{
    "model": "dashboard.room",
    "pk": 422,
    "fields": {
        "number": 422
    }
},
{
    "model": "dashboard.room",
    "pk": 423,
    "fields": {
        "number": 423
    }
},
{
    "model": "dashboard.room",
    "pk": 424,
    "fields": {
        "number": 424
    }
},
{
    "model": "dashboard.room",
    "pk": 425,
    "fields": {
        "number": 425
    }
},
{
    "model": "dashboard.room",
    "pk": 426,
    "fields": {
        "number": 426
    }
},
{
    "model": "dashboard.room",
    "pk": 427,
    "fields": {
        "number": 427
    }
},
{
    "model": "dashboard.room",
    "pk": 428,
    "fields": {
        "number": 428
    }
},
{
    "model": "dashboard.room",
    "pk": 429,
    "fields": {
        "number": 429
    }
},
{
    "model": "dashboard.room",
    "pk": 430,
    "fields": {
        "number": 430
    }
},
{
    "model": "dashboard.room",
    "pk": 431,
    "fields": {
        "number": 431
    }
},
{
    "model": "dashboard.room",
    "pk": 432,
    "fields": {
        "number": 432
    }
},
{
    "model": "dashboard.room",
    "pk": 433,
    "fields": {
        "number": 433
    }
},
{
    "model": "dashboard.room",
    "pk": 434,
    "fields": {
        "number": 434
    }
},
{
    "model": "dashboard.room",
    "pk": 435,
    "fields": {
        "number": 435
    }
},
{
    "model": "dashboard.room",
    "pk": 436,
    "fields": {
        "number": 436
    }
},
{
    "model": "dashboard.room",
    "pk": 437,
    "fields": {
        "number": 437
    }
},
{
    "model": "dashboard.room",
    "pk": 438,
    "fields": {
        "number": 438
    }
},
{
    "model": "dashboard.room",
    "pk": 439,
    "fields": {
        "number": 439
    }
},
{
    "model": "dashboard.room",
    "pk": 440,
    "fields": {
        "number": 440
    }
},
{
    "model": "dashboard.room",
    "pk": 441,
    "fields": {
        "number": 441
    }
},
{
    "model": "dashboard.room",
    "pk": 442,
    "fields": {
        "number": 442
    }
},
{
    "model": "dashboard.room",
    "pk": 443,
    "fields": {
        "number": 443
    }
},
{
    "model": "dashboard.room",
    "pk": 444,
    "fields": {
        "number": 444
    }
},
{
    "model": "dashboard.room",
    "pk": 445,
    "fields": {
        "number": 445
    }
},
{
    "model": "dashboard.room",
    "pk": 446,
    "fields": {
        "number": 446
    }
},
{
    "model": "dashboard.room",
    "pk": 447,
    "fields": {
        "number": 447
    }
},
{
    "model": "dashboard.room",
    "pk": 448,
    "fields": {
        "number": 448
    }
},
{
    "model": "dashboard.room",
    "pk": 449,
    "fields": {
        "number": 449
    }
},
{
    "model": "dashboard.room",
    "pk": 450,
    "fields": {
        "number": 450
    }
},
{
    "model": "dashboard.room",
    "pk": 451,
    "fields": {
        "number": 451
    }
},
{
    "model": "dashboard.room",
    "pk": 452,
    "fields": {
        "number": 452
    }
},
{
    "model": "dashboard.room",
    "pk": 453,
    "fields": {
        "number": 453
    }
},
{
    "model": "dashboard.room",
    "pk": 454,
    "fields": {
        "number": 454
    }
},
{
    "model": "dashboard.room",
    "pk": 455,
    "fields": {
        "number": 455
    }
},
{
    "model": "dashboard.room",
    "pk": 456,
    "fields": {
        "number": 456
    }
},
{
    "model": "dashboard.room",
    "pk": 457,
    "fields": {
        "number": 457
    }
},
{
    "model": "dashboard.room",
    "pk": 458,
    "fields": {
        "number": 458
    }
},
{
    "model": "dashboard.room",
    "pk": 459,
    "fields": {
        "number": 459
    }
},
{
    "model": "dashboard.room",
    "pk": 460,
    "fields": {
        "number": 460
    }
},
{
    "model": "dashboard.room",
    "pk": 461,
    "fields": {
        "number": 461
    }
},
{
    "model": "dashboard.room",
    "pk": 462,
    "fields": {
        "number": 462
    }
},
{
    "model": "dashboard.room",
    "pk": 463,
    "fields": {
        "number": 463
    }
},
{
    "model": "dashboard.room",
    "pk": 464,
    "fields": {
        "number": 464
    }
},
{
    "model": "dashboard.room",
    "pk": 465,
    "fields": {
        "number": 465
    }
},
{
    "model": "dashboard.room",
    "pk": 466,
    "fields": {
        "number": 466
    }
},
{
    "model": "dashboard.room",
    "pk": 467,
    "fields": {
        "number": 467
    }
},
{
    "model": "dashboard.room",
    "pk": 468,
    "fields": {
        "number": 468
    }
},
{
    "model": "dashboard.room",
    "pk": 469,
    "fields": {
        "number": 469
    }
},
{
    "model": "dashboard.room",
    "pk": 470,
    "fields": {
        "number": 470
    }
},
{
    "model": "dashboard.room",
    "pk": 471,
    "fields": {
        "number": 471
    }
},
{
    "model": "dashboard.room",
    "pk": 472,
    "fields": {
        "number": 472
    }
},
{
    "model": "dashboard.room",
    "pk": 473,
    "fields": {
        "number": 473
    }
},
{
    "model": "dashboard.room",
    "pk": 474,
    "fields": {
        "number": 474
    }
},
{
    "model": "dashboard.room",
    "pk": 475,
    "fields": {
        "number": 475
    }
},
{
    "model": "dashboard.room",
    "pk": 476,
    "fields": {
        "number": 476
    }
},
{
    "model": "dashboard.room",
    "pk": 477,
    "fields": {
        "number": 477
    }
},
{
    "model": "dashboard.room",
    "pk": 478,
    "fields": {
        "number": 478
    }
},
{
    "model": "dashboard.room",
    "pk": 479,
    "fields": {
        "number": 479
    }
},
{
    "model": "dashboard.room",
    "pk": 480,
    "fields": {
        "number": 480
    }
},
{
    "model": "dashboard.room",
    "pk": 481,
    "fields": {
        "number": 481
    }
},
{
    "model": "dashboard.room",
    "pk": 482,
    "fields": {
        "number": 482
    }
},
{
    "model": "dashboard.room",
    "pk": 483,
    "fields": {
        "number": 483
    }
},
{
    "model": "dashboard.room",
    "pk": 484,
    "fields": {
        "number": 484
    }
},
{
    "model": "dashboard.room",
    "pk": 485,
    "fields": {
        "number": 485
    }
},
{
    "model": "dashboard.room",
    "pk": 486,
    "fields": {
        "number": 486
    }
},
{
    "model": "dashboard.room",
    "pk": 487,
    "fields": {
        "number": 487
    }
},
{
    "model": "dashboard.room",
    "pk": 488,
    "fields": {
        "number": 488
    }
},
{
    "model": "dashboard.room",
    "pk": 489,
    "fields": {
        "number": 489
    }
},
{
    "model": "dashboard.room",
    "pk": 490,
    "fields": {
        "number": 490
    }
},
{
    "model": "dashboard.room",
    "pk": 491,
    "fields": {
        "number": 491
    }
},
{
    "model": "dashboard.room",
    "pk": 492,
    "fields": {
        "number": 492
    }
},
{
    "model": "dashboard.room",
    "pk": 493,
    "fields": {
        "number": 493
    }
},
{
    "model": "dashboard.room",
    "pk": 494,
    "fields": {
        "number": 494
    }
},
{
    "model": "dashboard.room",
    "pk": 495,
    "fields": {
        "number": 495
    }
},
{
    "model": "dashboard.room",
    "pk": 496,
    "fields": {
        "number": 496
    }
},
{
    "model": "dashboard.room",
    "pk": 497,
    "fields": {
        "number": 497
    }
},
{
    "model": "dashboard.room",
    "pk": 498,
    "fields": {
        "number": 498
    }
},
{
    "model": "dashboard.room",
    "pk": 499,
    "fields": {
        "number": 499
    }
},
{
    "model": "dashboard.room",
    "pk": 500,
    "fields": {
        "number": 500
    }
},
{
    "model": "dashboard.room",
    "pk": 501,
    "fields": {
        "number": 501
    }
},
{
    "model": "dashboard.room",
    "pk": 502,
    "fields": {
        "number": 502
    }
},
{
    "model": "dashboard.room",
    "pk": 503,
    "fields": {
        "number": 503
    }
},
{
    "model": "dashboard.room",
    "pk": 504,
    "fields": {
        "number": 504
    }
},
{
    "model": "dashboard.room",
    "pk": 505,
    "fields": {
        "number": 505
    }
},
{
    "model": "dashboard.room",
    "pk": 506,
    "fields": {
        "number": 506
    }
},
{
    "model": "dashboard.room",
    "pk": 507,
    "fields": {
        "number": 507
    }
},
{
    "model": "dashboard.room",
    "pk": 508,
    "fields": {
        "number": 508
    }
},
{
    "model": "dashboard.room",
    "pk": 509,
    "fields": {
        "number": 509
    }
},
{
    "model": "dashboard.room",
    "pk": 510,
    "fields": {
        "number": 510
    }
},
{
    "model": "dashboard.room",
    "pk": 511,
    "fields": {
        "number": 511
    }
},
{
    "model": "dashboard.room",
    "pk": 512,
    "fields": {
        "number": 512
    }
},
{
    "model": "dashboard.room",
    "pk": 513,
    "fields": {
        "number": 513
    }
},
{
    "model": "dashboard.room",
    "pk": 514,
    "fields": {
        "number": 514
    }
},
{
    "model": "dashboard.room",
    "pk": 515,
    "fields": {
        "number": 515
    }
},
{
    "model": "dashboard.room",
    "pk": 516,
    "fields": {
        "number": 516
    }
},
{
    "model": "dashboard.room",
    "pk": 517,
    "fields": {
        "number": 517
    }
},
{
    "model": "dashboard.room",
    "pk": 518,
    "fields": {
        "number": 518
    }
},
{
    "model": "dashboard.room",
    "pk": 519,
    "fields": {
        "number": 519
    }
},
{
    "model": "dashboard.room",
    "pk": 520,
    "fields": {
        "number": 520
    }
},
{
    "model": "dashboard.room",
    "pk": 521,
    "fields": {
        "number": 521
    }
},
{
    "model": "dashboard.room",
    "pk": 522,
    "fields": {
        "number": 522
    }
},
{
    "model": "dashboard.room",
    "pk": 523,
    "fields": {
        "number": 523
    }
},
{
    "model": "dashboard.room",
    "pk": 524,
    "fields": {
        "number": 524
    }
},
{
    "model": "dashboard.room",
    "pk": 525,
    "fields": {
        "number": 525
    }
},
{
    "model": "dashboard.room",
    "pk": 526,
    "fields": {
        "number": 526
    }
},
{
    "model": "dashboard.room",
    "pk": 527,
    "fields": {
        "number": 527
    }
},
{
    "model": "dashboard.room",
    "pk": 528,
    "fields": {
        "number": 528
    }
},
{
    "model": "dashboard.room",
    "pk": 529,
    "fields": {
        "number": 529
    }
},
{
    "model": "dashboard.room",
    "pk": 530,
    "fields": {
        "number": 530
    }
},
{
    "model": "dashboard.room",
    "pk": 531,
    "fields": {
        "number": 531
    }
},
{
    "model": "dashboard.room",
    "pk": 532,
    "fields": {
        "number": 532
    }
},
{
    "model": "dashboard.room",
    "pk": 533,
    "fields": {
        "number": 533
    }
},
{
    "model": "dashboard.room",
    "pk": 534,
    "fields": {
        "number": 534
    }
},
{
    "model": "dashboard.room",
    "pk": 535,
    "fields": {
        "number": 535
    }
},
{
    "model": "dashboard.room",
    "pk": 536,
    "fields": {
        "number": 536
    }
},
{
    "model": "dashboard.room",
    "pk": 537,
    "fields": {
        "number": 537
    }
},
{
    "model": "dashboard.room",
    "pk": 538,
    "fields": {
        "number": 538
    }
},
{
    "model": "dashboard.room",
    "pk": 539,
    "fields": {
        "number": 539
    }
},
{
    "model": "dashboard.room",
    "pk": 540,
    "fields": {
        "number": 540
    }
},
{
    "model": "dashboard.room",
    "pk": 541,
    "fields": {
        "number": 541
    }
},
{
    "model": "dashboard.room",
    "pk": 542,
    "fields": {
        "number": 542
    }
},
{
    "model": "dashboard.room",
    "pk": 543,
    "fields": {
        "number": 543
    }
},
{
    "model": "dashboard.room",
    "pk": 544,
    "fields": {
        "number": 544
    }
},
{
    "model": "dashboard.room",
    "pk": 545,
    "fields": {
        "number": 545
    }
},
{
    "model": "dashboard.room",
    "pk": 546,
    "fields": {
        "number": 546
    }
},
{
    "model": "dashboard.room",
    "pk": 547,
    "fields": {
        "number": 547
    }
},
{
    "model": "dashboard.room",
    "pk": 548,
    "fields": {
        "number": 548
    }
},
{
    "model": "dashboard.room",
    "pk": 549,
    "fields": {
        "number": 549
    }
},
{
    "model": "dashboard.room",
    "pk": 550,
    "fields": {
        "number": 550
    }
},
{
    "model": "dashboard.room",
    "pk": 551,
    "fields": {
        "number": 551
    }
},
{
    "model": "dashboard.room",
    "pk": 552,
    "fields": {
        "number": 552
    }
},
{
    "model": "dashboard.room",
    "pk": 553,
    "fields": {
        "number": 553
    }
},
{
    "model": "dashboard.room",
    "pk": 554,
    "fields": {
        "number": 554
    }
},
{
    "model": "dashboard.room",
    "pk": 555,
    "fields": {
        "number": 555
    }
},
{
    "model": "dashboard.room",
    "pk": 556,
    "fields": {
        "number": 556
    }
},
{
    "model": "dashboard.room",
    "pk": 557,
    "fields": {
        "number": 557
    }
},
{
    "model": "dashboard.room",
    "pk": 558,
    "fields": {
        "number": 558
    }
},
{
    "model": "dashboard.room",
    "pk": 559,
    "fields": {
        "number": 559
    }
},
{
    "model": "dashboard.room",
    "pk": 560,
    "fields": {
        "number": 560
    }
},
{
    "model": "dashboard.room",
    "pk": 561,
    "fields": {
        "number": 561
    }
},
{
    "model": "dashboard.room",
    "pk": 562,
    "fields": {
        "number": 562
    }
},
{
    "model": "dashboard.room",
    "pk": 563,
    "fields": {
        "number": 563
    }
},
{
    "model": "dashboard.room",
    "pk": 564,
    "fields": {
        "number": 564
    }
},
{
    "model": "dashboard.room",
    "pk": 565,
    "fields": {
        "number": 565
    }
},
{
    "model": "dashboard.room",
    "pk": 566,
    "fields": {
        "number": 566
    }
},
{
    "model": "dashboard.room",
    "pk": 567,
    "fields": {
        "number": 567
    }
},
{
    "model": "dashboard.room",
    "pk": 568,
    "fields": {
        "number": 568
    }
},
{
    "model": "dashboard.room",
    "pk": 569,
    "fields": {
        "number": 569
    }
},
{
    "model": "dashboard.room",
    "pk": 570,
    "fields": {
        "number": 570
    }
},
{
    "model": "dashboard.room",
    "pk": 571,
    "fields": {
        "number": 571
    }
},
{
    "model": "dashboard.room",
    "pk": 572,
    "fields": {
        "number": 572
    }
},
{
    "model": "dashboard.room",
    "pk": 573,
    "fields": {
        "number": 573
    }
},
{
    "model": "dashboard.room",
    "pk": 574,
    "fields": {
        "number": 574
    }
},
{
    "model": "dashboard.room",
    "pk": 575,
    "fields": {
        "number": 575
    }
},
{
    "model": "dashboard.room",
    "pk": 576,
    "fields": {
        "number": 576
    }
},
{
    "model": "dashboard.room",
    "pk": 577,
    "fields": {
        "number": 577
    }
},
{
    "model": "dashboard.room",
    "pk": 578,
    "fields": {
        "number": 578
    }
},
{
    "model": "dashboard.room",
    "pk": 579,
    "fields": {
        "number": 579
    }
},
{
    "model": "dashboard.room",
    "pk": 580,
    "fields": {
        "number": 580
    }
},
{
    "model": "dashboard.room",
    "pk": 581,
    "fields": {
        "number": 581
    }
},
{
    "model": "dashboard.room",
    "pk": 582,
    "fields": {
        "number": 582
    }
},
{
    "model": "dashboard.room",
    "pk": 583,
    "fields": {
        "number": 583
    }
},
{
    "model": "dashboard.room",
    "pk": 584,
    "fields": {
        "number": 584
    }
},
{
    "model": "dashboard.room",
    "pk": 585,
    "fields": {
        "number": 585
    }
},
{
    "model": "dashboard.room",
    "pk": 586,
    "fields": {
        "number": 586
    }
},
{
    "model": "dashboard.room",
    "pk": 587,
    "fields": {
        "number": 587
    }
},
{
    "model": "dashboard.room",
    "pk": 588,
    "fields": {
        "number": 588
    }
},
{
    "model": "dashboard.room",
    "pk": 589,
    "fields": {
        "number": 589
    }
},
{
    "model": "dashboard.room",
    "pk": 590,
    "fields": {
        "number": 590
    }
},
{
    "model": "dashboard.room",
    "pk": 591,
    "fields": {
        "number": 591
    }
},
{
    "model": "dashboard.room",
    "pk": 592,
    "fields": {
        "number": 592
    }
},
{
    "model": "dashboard.room",
    "pk": 593,
    "fields": {
        "number": 593
    }
},
{
    "model": "dashboard.room",
    "pk": 594,
    "fields": {
        "number": 594
    }
},
{
    "model": "dashboard.room",
    "pk": 595,
    "fields": {
        "number": 595
    }
},
{
    "model": "dashboard.room",
    "pk": 596,
    "fields": {
        "number": 596
    }
},
{
    "model": "dashboard.room",
    "pk": 597,
    "fields": {
        "number": 597
    }
},
{
    "model": "dashboard.room",
    "pk": 598,
    "fields": {
        "number": 598
    }
},
{
    "model": "dashboard.room",
    "pk": 599,
    "fields": {
        "number": 599
    }
},
{
    "model": "dashboard.room",
    "pk": 600,
    "fields": {
        "number": 600
    }
},
{
    "model": "dashboard.room",
    "pk": 601,
    "fields": {
        "number": 601
    }
},
{
    "model": "dashboard.room",
    "pk": 602,
    "fields": {
        "number": 602
    }
},
{
    "model": "dashboard.room",
    "pk": 603,
    "fields": {
        "number": 603
    }
},
{
    "model": "dashboard.room",
    "pk": 604,
    "fields": {
        "number": 604
    }
},
{
    "model": "dashboard.room",
    "pk": 605,
    "fields": {
        "number": 605
    }
},
{
    "model": "dashboard.room",
    "pk": 606,
    "fields": {
        "number": 606
    }
},
{
    "model": "dashboard.room",
    "pk": 607,
    "fields": {
        "number": 607
    }
},
{
    "model": "dashboard.room",
    "pk": 608,
    "fields": {
        "number": 608
    }
},
{
    "model": "dashboard.room",
    "pk": 609,
    "fields": {
        "number": 609
    }
},
{
    "model": "dashboard.room",
    "pk": 610,
    "fields": {
        "number": 610
    }
},
{
    "model": "dashboard.room",
    "pk": 611,
    "fields": {
        "number": 611
    }
},
{
    "model": "dashboard.room",
    "pk": 612,
    "fields": {
        "number": 612
    }
},
{
    "model": "dashboard.room",
    "pk": 613,
    "fields": {
        "number": 613
    }
},
{
    "model": "dashboard.room",
    "pk": 614,
    "fields": {
        "number": 614
    }
},
{
    "model": "dashboard.room",
    "pk": 615,
    "fields": {
        "number": 615
    }
},
{
    "model": "dashboard.room",
    "pk": 616,
    "fields": {
        "number": 616
    }
},
{
    "model": "dashboard.room",
    "pk": 617,
    "fields": {
        "number": 617
    }
},
{
    "model": "dashboard.room",
    "pk": 618,
    "fields": {
        "number": 618
    }
},
{
    "model": "dashboard.room",
    "pk": 619,
    "fields": {
        "number": 619
    }
},
{
    "model": "dashboard.room",
    "pk": 620,
    "fields": {
        "number": 620
    }
},
{
    "model": "dashboard.room",
    "pk": 621,
    "fields": {
        "number": 621
    }
},
{
    "model": "dashboard.room",
    "pk": 622,
    "fields": {
        "number": 622
    }
},
{
    "model": "dashboard.room",
    "pk": 623,
    "fields": {
        "number": 623
    }
},
{
    "model": "dashboard.room",
    "pk": 624,
    "fields": {
        "number": 624
    }
},
{
    "model": "dashboard.room",
    "pk": 625,
    "fields": {
        "number": 625
    }
},
{
    "model": "dashboard.room",
    "pk": 626,
    "fields": {
        "number": 626
    }
},
{
    "model": "dashboard.room",
    "pk": 627,
    "fields": {
        "number": 627
    }
},
{
    "model": "dashboard.room",
    "pk": 628,
    "fields": {
        "number": 628
    }
},
{
    "model": "dashboard.room",
    "pk": 629,
    "fields": {
        "number": 629
    }
},
{
    "model": "dashboard.room",
    "pk": 630,
    "fields": {
        "number": 630
    }
},
{
    "model": "dashboard.room",
    "pk": 631,
    "fields": {
        "number": 631
    }
},
{
    "model": "dashboard.room",
    "pk": 632,
    "fields": {
        "number": 632
    }
},
{
    "model": "dashboard.room",
    "pk": 633,
    "fields": {
        "number": 633
    }
},
{
    "model": "dashboard.room",
    "pk": 634,
    "fields": {
        "number": 634
    }
},
{
    "model": "dashboard.room",
    "pk": 635,
    "fields": {
        "number": 635
    }
},
{
    "model": "dashboard.room",
    "pk": 636,
    "fields": {
        "number": 636
    }
},
{
    "model": "dashboard.room",
    "pk": 637,
    "fields": {
        "number": 637
    }
},
{
    "model": "dashboard.room",
    "pk": 638,
    "fields": {
        "number": 638
    }
},
{
    "model": "dashboard.room",
    "pk": 639,
    "fields": {
        "number": 639
    }
},
{
    "model": "dashboard.room",
    "pk": 640,
    "fields": {
        "number": 640
    }
},
{
    "model": "dashboard.room",
    "pk": 641,
    "fields": {
        "number": 641
    }
},
{
    "model": "dashboard.room",
    "pk": 642,
    "fields": {
        "number": 642
    }
},
{
    "model": "dashboard.room",
    "pk": 643,
    "fields": {
        "number": 643
    }
},
{
    "model": "dashboard.room",
    "pk": 644,
    "fields": {
        "number": 644
    }
},
{
    "model": "dashboard.room",
    "pk": 645,
    "fields": {
        "number": 645
    }
},
{
    "model": "dashboard.room",
    "pk": 646,
    "fields": {
        "number": 646
    }
},
{
    "model": "dashboard.room",
    "pk": 647,
    "fields": {
        "number": 647
    }
},
{
    "model": "dashboard.room",
    "pk": 648,
    "fields": {
        "number": 648
    }
},
{
    "model": "dashboard.room",
    "pk": 649,
    "fields": {
        "number": 649
    }
},
{
    "model": "dashboard.room",
    "pk": 650,
    "fields": {
        "number": 650
    }
},
{
    "model": "dashboard.room",
    "pk": 651,
    "fields": {
        "number": 651
    }
},
{
    "model": "dashboard.room",
    "pk": 652,
    "fields": {
        "number": 652
    }
},
{
    "model": "dashboard.room",
    "pk": 653,
    "fields": {
        "number": 653
    }
},
{
    "model": "dashboard.room",
    "pk": 654,
    "fields": {
        "number": 654
    }
},
{
    "model": "dashboard.room",
    "pk": 655,
    "fields": {
        "number": 655
    }
},
{
    "model": "dashboard.room",
    "pk": 656,
    "fields": {
        "number": 656
    }
},
{
    "model": "dashboard.room",
    "pk": 657,
    "fields": {
        "number": 657
    }
},
{
    "model": "dashboard.room",
    "pk": 658,
    "fields": {
        "number": 658
    }
},
{
    "model": "dashboard.room",
    "pk": 659,
    "fields": {
        "number": 659
    }
},
{
    "model": "dashboard.room",
    "pk": 660,
    "fields": {
        "number": 660
    }
},
{
    "model": "dashboard.room",
    "pk": 661,
    "fields": {
        "number": 661
    }
},
{
    "model": "dashboard.room",
    "pk": 662,
    "fields": {
        "number": 662
    }
},
{
    "model": "dashboard.room",
    "pk": 663,
    "fields": {
        "number": 663
    }
},
{
    "model": "dashboard.room",
    "pk": 664,
    "fields": {
        "number": 664
    }
},
{
    "model": "dashboard.room",
    "pk": 665,
    "fields": {
        "number": 665
    }
},
{
    "model": "dashboard.room",
    "pk": 666,
    "fields": {
        "number": 666
    }
},
{
    "model": "dashboard.room",
    "pk": 667,
    "fields": {
        "number": 667
    }
},
{
    "model": "dashboard.room",
    "pk": 668,
    "fields": {
        "number": 668
    }
},
{
    "model": "dashboard.room",
    "pk": 669,
    "fields": {
        "number": 669
    }
},
{
    "model": "dashboard.room",
    "pk": 670,
    "fields": {
        "number": 670
    }
},
{
    "model": "dashboard.room",
    "pk": 671,
    "fields": {
        "number": 671
    }
},
{
    "model": "dashboard.room",
    "pk": 672,
    "fields": {
        "number": 672
    }
},
{
    "model": "dashboard.room",
    "pk": 673,
    "fields": {
        "number": 673
    }
},
{
    "model": "dashboard.room",
    "pk": 674,
    "fields": {
        "number": 674
    }
},
{
    "model": "dashboard.room",
    "pk": 675,
    "fields": {
        "number": 675
    }
},
{
    "model": "dashboard.room",
    "pk": 676,
    "fields": {
        "number": 676
    }
},
{
    "model": "dashboard.room",
    "pk": 677,
    "fields": {
        "number": 677
    }
},
{
    "model": "dashboard.room",
    "pk": 678,
    "fields": {
        "number": 678
    }
},
{
    "model": "dashboard.room",
    "pk": 679,
    "fields": {
        "number": 679
    }
},
{
    "model": "dashboard.room",
    "pk": 680,
    "fields": {
        "number": 680
    }
},
{
    "model": "dashboard.room",
    "pk": 681,
    "fields": {
        "number": 681
    }
},
{
    "model": "dashboard.room",
    "pk": 682,
    "fields": {
        "number": 682
    }
},
{
    "model": "dashboard.room",
    "pk": 683,
    "fields": {
        "number": 683
    }
},
{
    "model": "dashboard.room",
    "pk": 684,
    "fields": {
        "number": 684
    }
},
{
    "model": "dashboard.room",
    "pk": 685,
    "fields": {
        "number": 685
    }
},
{
    "model": "dashboard.room",
    "pk": 686,
    "fields": {
        "number": 686
    }
},
{
    "model": "dashboard.room",
    "pk": 687,
    "fields": {
        "number": 687
    }
},
{
    "model": "dashboard.room",
    "pk": 688,
    "fields": {
        "number": 688
    }
},
{
    "model": "dashboard.room",
    "pk": 689,
    "fields": {
        "number": 689
    }
},
{
    "model": "dashboard.room",
    "pk": 690,
    "fields": {
        "number": 690
    }
},
{
    "model": "dashboard.room",
    "pk": 691,
    "fields": {
        "number": 691
    }
},
{
    "model": "dashboard.room",
    "pk": 692,
    "fields": {
        "number": 692
    }
},
{
    "model": "dashboard.room",
    "pk": 693,
    "fields": {
        "number": 693
    }
},
{
    "model": "dashboard.room",
    "pk": 694,
    "fields": {
        "number": 694
    }
},
{
    "model": "dashboard.room",
    "pk": 695,
    "fields": {
        "number": 695
    }
},
{
    "model": "dashboard.room",
    "pk": 696,
    "fields": {
        "number": 696
    }
},
{
    "model": "dashboard.room",
    "pk": 697,
    "fields": {
        "number": 697
    }
},
{
    "model": "dashboard.room",
    "pk": 698,
    "fields": {
        "number": 698
    }
},
{
    "model": "dashboard.room",
    "pk": 699,
    "fields": {
        "number": 699
    }
},
{
    "model": "dashboard.room",
    "pk": 700,
    "fields": {
        "number": 700
    }
},
{
    "model": "contenttypes.contenttype",
    "pk": 1,
    "fields": {
        "app_label": "dashboard",
        "model": "parcel"
    }
},
{
    "model": "contenttypes.contenttype",
    "pk": 2,
    "fields": {
        "app_label": "dashboard",
        "model": "resident"
    }
},
{
    "model": "contenttypes.contenttype",
    "pk": 3,
    "fields": {
        "app_label": "dashboard",
        "model": "room"
    }
},
{
    "model": "contenttypes.contenttype",
    "pk": 4,
    "fields": {
        "app_label": "admin",
        "model": "logentry"
    }
},
{
    "model": "contenttypes.contenttype",
    "pk": 5,
    "fields": {
        "app_label": "auth",
        "model": "permission"
    }
},
{
    "model": "contenttypes.contenttype",
    "pk": 6,
    "fields": {
        "app_label": "auth",
        "model": "group"
    }
},
{
    "model": "contenttypes.contenttype",
    "pk": 7,
    "fields": {
        "app_label": "auth",
        "model": "user"
    }
},
{
    "model": "contenttypes.contenttype",
    "pk": 8,
    "fields": {
        "app_label": "contenttypes",
        "model": "contenttype"
    }
},
{
    "model": "contenttypes.contenttype",
    "pk": 9,
    "fields": {
        "app_label": "sessions",
        "model": "session"
    }
},
{
    "model": "auth.permission",
    "pk": 1,
    "fields": {
        "name": "Can add parcel",
        "content_type": 1,
        "codename": "add_parcel"
    }
},
{
    "model": "auth.permission",
    "pk": 2,
    "fields": {
        "name": "Can change parcel",
        "content_type": 1,
        "codename": "change_parcel"
    }
},
{
    "model": "auth.permission",
    "pk": 3,
    "fields": {
        "name": "Can delete parcel",
        "content_type": 1,
        "codename": "delete_parcel"
    }
},
{
    "model": "auth.permission",
    "pk": 4,
    "fields": {
        "name": "Can add resident",
        "content_type": 2,
        "codename": "add_resident"
    }
},
{
    "model": "auth.permission",
    "pk": 5,
    "fields": {
        "name": "Can change resident",
        "content_type": 2,
        "codename": "change_resident"
    }
},
{
    "model": "auth.permission",
    "pk": 6,
    "fields": {
        "name": "Can delete resident",
        "content_type": 2,
        "codename": "delete_resident"
    }
},
{
    "model": "auth.permission",
    "pk": 7,
    "fields": {
        "name": "Can add room",
        "content_type": 3,
        "codename": "add_room"
    }
},
{
    "model": "auth.permission",
    "pk": 8,
    "fields": {
        "name": "Can change room",
        "content_type": 3,
        "codename": "change_room"
    }
},
{
    "model": "auth.permission",
    "pk": 9,
    "fields": {
        "name": "Can delete room",
        "content_type": 3,
        "codename": "delete_room"
    }
},
{
    "model": "auth.permission",
    "pk": 10,
    "fields": {
        "name": "Can add log entry",
        "content_type": 4,
        "codename": "add_logentry"
    }
},
{
    "model": "auth.permission",
    "pk": 11,
    "fields": {
        "name": "Can change log entry",
        "content_type": 4,
        "codename": "change_logentry"
    }
},
{
    "model": "auth.permission",
    "pk": 12,
    "fields": {
        "name": "Can delete log entry",
        "content_type": 4,
        "codename": "delete_logentry"
    }
},
{
    "model": "auth.permission",
    "pk": 13,
    "fields": {
        "name": "Can add permission",
        "content_type": 5,
        "codename": "add_permission"
    }
},
{
    "model": "auth.permission",
    "pk": 14,
    "fields": {
        "name": "Can change permission",
        "content_type": 5,
        "codename": "change_permission"
    }
},
{
    "model": "auth.permission",
    "pk": 15,
    "fields": {
        "name": "Can delete permission",
        "content_type": 5,
        "codename": "delete_permission"
    }
},
{
    "model": "auth.permission",
    "pk": 16,
    "fields": {
        "name": "Can add group",
        "content_type": 6,
        "codename": "add_group"
    }
},
{
    "model": "auth.permission",
    "pk": 17,
    "fields": {
        "name": "Can change group",
        "content_type": 6,
        "codename": "change_group"
    }
},
{
    "model": "auth.permission",
    "pk": 18,
    "fields": {
        "name": "Can delete group",
        "content_type": 6,
        "codename": "delete_group"
    }
},
{
    "model": "auth.permission",
    "pk": 19,
    "fields": {
        "name": "Can add user",
        "content_type": 7,
        "codename": "add_user"
    }
},
{
    "model": "auth.permission",
    "pk": 20,
    "fields": {
        "name": "Can change user",
        "content_type": 7,
        "codename": "change_user"
    }
},
{
    "model": "auth.permission",
    "pk": 21,
    "fields": {
        "name": "Can delete user",
        "content_type": 7,
        "codename": "delete_user"
    }
},
{
    "model": "auth.permission",
    "pk": 22,
    "fields": {
        "name": "Can add content type",
        "content_type": 8,
        "codename": "add_contenttype"
    }
},
{
    "model": "auth.permission",
    "pk": 23,
    "fields": {
        "name": "Can change content type",
        "content_type": 8,
        "codename": "change_contenttype"
    }
},
{
    "model": "auth.permission",
    "pk": 24,
    "fields": {
        "name": "Can delete content type",
        "content_type": 8,
        "codename": "delete_contenttype"
    }
},
{
    "model": "auth.permission",
    "pk": 25,
    "fields": {
        "name": "Can add session",
        "content_type": 9,
        "codename": "add_session"
    }
},
{
    "model": "auth.permission",
    "pk": 26,
    "fields": {
        "name": "Can change session",
        "content_type": 9,
        "codename": "change_session"
    }
},
{
    "model": "auth.permission",
    "pk": 27,
    "fields": {
        "name": "Can delete session",
        "content_type": 9,
        "codename": "delete_session"
    }
},
{
    "model": "auth.user",
    "pk": 1,
    "fields": {
        "password": "pbkdf2_sha256$36000$aLNnZZyAqFh5$kHcEyMmelRbDRJxDvWHOy8AGUbNU0QNsp38cYr8RwVM=",
        "last_login": null,
        "is_superuser": true,
        "username": "admin",
        "first_name": "",
        "last_name": "",
        "email": "pishias92@gmail.com",
        "is_staff": true,
        "is_active": true,
        "date_joined": "2017-12-02T14:34:05.104Z",
        "groups": [],
        "user_permissions": []
    }
}
]
